thousandeyes_sdk/agents/__init__.py
thousandeyes_sdk/agents/py.typed
thousandeyes_sdk/agents/api/__init__.py
thousandeyes_sdk/agents/api/agent_proxies_api.py
thousandeyes_sdk/agents/api/cloud_and_enterprise_agent_notification_rules_api.py
thousandeyes_sdk/agents/api/cloud_and_enterprise_agents_api.py
thousandeyes_sdk/agents/api/enterprise_agent_cluster_api.py
thousandeyes_sdk/agents/api/tests_assignment_on_agents_api.py
thousandeyes_sdk/agents/models/__init__.py
thousandeyes_sdk/agents/models/account_group.py
thousandeyes_sdk/agents/models/agent_base.py
thousandeyes_sdk/agents/models/agent_cluster_assign_request.py
thousandeyes_sdk/agents/models/agent_cluster_unassign_request.py
thousandeyes_sdk/agents/models/agent_details.py
thousandeyes_sdk/agents/models/agent_details_expand.py
thousandeyes_sdk/agents/models/agent_ipv6_policy.py
thousandeyes_sdk/agents/models/agent_label.py
thousandeyes_sdk/agents/models/agent_list_expand.py
thousandeyes_sdk/agents/models/agent_notification.py
thousandeyes_sdk/agents/models/agent_proxies.py
thousandeyes_sdk/agents/models/agent_proxy.py
thousandeyes_sdk/agents/models/agent_request.py
thousandeyes_sdk/agents/models/agent_response.py
thousandeyes_sdk/agents/models/agent_tests_assign_request.py
thousandeyes_sdk/agents/models/alert_email.py
thousandeyes_sdk/agents/models/alert_integration_base.py
thousandeyes_sdk/agents/models/alert_integration_type.py
thousandeyes_sdk/agents/models/cloud_agent_detail.py
thousandeyes_sdk/agents/models/cloud_enterprise_agent.py
thousandeyes_sdk/agents/models/cloud_enterprise_agent_type.py
thousandeyes_sdk/agents/models/cloud_enterprise_agents.py
thousandeyes_sdk/agents/models/cluster_member.py
thousandeyes_sdk/agents/models/coordinates.py
thousandeyes_sdk/agents/models/enterprise_agent.py
thousandeyes_sdk/agents/models/enterprise_agent_cluster_detail.py
thousandeyes_sdk/agents/models/enterprise_agent_data.py
thousandeyes_sdk/agents/models/enterprise_agent_detail.py
thousandeyes_sdk_agents-2.23.0.dist-info/licenses/LICENSE
thousandeyes_sdk_agents-2.23.0.dist-info/licenses/NOTICE
thousandeyes_sdk_agents-2.23.0.dist-info/METADATA
thousandeyes_sdk_agents-2.23.0.dist-info/WHEEL
thousandeyes_sdk_agents-2.23.0.dist-info/top_level.txt
thousandeyes_sdk_agents-2.23.0.dist-info/RECORD
